{"mockup":{"controls":{"control":[{"ID":"1","h":"480","measuredH":"400","measuredW":"450","properties":{"text":"Grimp'EPFC"},"typeID":"TitleWindow","w":"720","x":"41","y":"80","zOrder":"0"},{"ID":"4","measuredH":"45","measuredW":"229","properties":{"bold":"true","text":"Grimp'EPFC","underline":"true"},"typeID":"Title","x":"292","y":"157","zOrder":"1"},{"ID":"5","measuredH":"27","measuredW":"56","properties":{"text":"Login"},"typeID":"Button","x":"373","y":"267","zOrder":"2"},{"ID":"6","measuredH":"27","measuredW":"66","properties":{"text":"Signup"},"typeID":"Button","x":"368","y":"320","zOrder":"3"}]},"measuredH":"560","measuredW":"761","mockupH":"480","mockupW":"720","version":"1.0"}}